{
  "rows": [
    {
      "symbol": "2330",
      "market": "twse",
      "name": "台積電",
      "price": 2390,
      "changePercent": -4.016064257028113,
      "dollarVolume": 158973915280,
      "marketCap": 61978364460130,
      "sector": "半導體業",
      "theme": "晶圓代工",
      "isNew": false,
      "rankChange": 1,
      "streak": 68
    },
    {
      "symbol": "2303",
      "market": "twse",
      "name": "聯電",
      "price": 178,
      "changePercent": 4.705882352941177,
      "dollarVolume": 99457017110,
      "marketCap": 2238703306860,
      "sector": "半導體業",
      "theme": "晶圓代工",
      "isNew": false,
      "rankChange": -1,
      "streak": 49
    },
    {
      "symbol": "3481",
      "market": "twse",
      "name": "群創",
      "price": 69.4,
      "changePercent": 5.151515151515151,
      "dollarVolume": 76532404822,
      "marketCap": 554450295187.8,
      "sector": "光電業",
      "theme": "面板",
      "isNew": false,
      "rankChange": 3,
      "streak": 6
    },
    {
      "symbol": "2454",
      "market": "twse",
      "name": "聯發科",
      "price": 4285,
      "changePercent": -5.512679162072767,
      "dollarVolume": 70824423930,
      "marketCap": 6872691818995,
      "sector": "半導體業",
      "theme": "IC 設計",
      "isNew": false,
      "rankChange": -1,
      "streak": 68
    },
    {
      "symbol": "2408",
      "market": "twse",
      "name": "南亞科",
      "price": 443.5,
      "changePercent": -2.42024202420242,
      "dollarVolume": 55311194856,
      "marketCap": 1530166313989,
      "sector": "半導體業",
      "theme": "記憶體",
      "isNew": false,
      "rankChange": -1,
      "streak": 68
    },
    {
      "symbol": "2344",
      "market": "twse",
      "name": "華邦電",
      "price": 205,
      "changePercent": -3.0732860520094563,
      "dollarVolume": 51759138408,
      "marketCap": 922500039565,
      "sector": "半導體業",
      "theme": "記憶體",
      "isNew": false,
      "rankChange": -1,
      "streak": 68
    },
    {
      "symbol": "2327",
      "market": "twse",
      "name": "國巨*",
      "price": 1050,
      "changePercent": 2.941176470588235,
      "dollarVolume": 50659977740,
      "marketCap": 2175038758200,
      "sector": "電子零組件業",
      "theme": "被動元件",
      "isNew": false,
      "rankChange": 0,
      "streak": 54
    },
    {
      "symbol": "2308",
      "market": "twse",
      "name": "台達電",
      "price": 2000,
      "changePercent": -3.8461538461538463,
      "dollarVolume": 47522219030,
      "marketCap": 5195086658000,
      "sector": "電子零組件業",
      "theme": "電源管理",
      "isNew": false,
      "rankChange": 4,
      "streak": 68
    },
    {
      "symbol": "6770",
      "market": "twse",
      "name": "力積電",
      "price": 85.7,
      "changePercent": 9.033078880407123,
      "dollarVolume": 38821173558,
      "marketCap": 399687978375.5,
      "sector": "半導體業",
      "theme": "晶圓代工",
      "isNew": false,
      "rankChange": -1,
      "streak": 7
    },
    {
      "symbol": "2409",
      "market": "twse",
      "name": "友達",
      "price": 30.5,
      "changePercent": 4.991394148020654,
      "dollarVolume": 27272349411,
      "marketCap": 230186518646,
      "sector": "光電業",
      "theme": "面板",
      "isNew": false,
      "rankChange": 4,
      "streak": 5
    },
    {
      "symbol": "3037",
      "market": "twse",
      "name": "欣興",
      "price": 931,
      "changePercent": -4.414784394250513,
      "dollarVolume": 25331936392,
      "marketCap": 1479240722036,
      "sector": "電子零組件業",
      "theme": "ABF 載板",
      "isNew": false,
      "rankChange": 5,
      "streak": 42
    },
    {
      "symbol": "3711",
      "market": "twse",
      "name": "日月光投控",
      "price": 653,
      "changePercent": -1.3595166163141994,
      "dollarVolume": 22851001408,
      "marketCap": 2912924002546,
      "sector": "半導體業",
      "theme": "封測",
      "isNew": false,
      "rankChange": 1,
      "streak": 62
    },
    {
      "symbol": "8046",
      "market": "twse",
      "name": "南電",
      "price": 955,
      "changePercent": 5.060506050605061,
      "dollarVolume": 22817592612,
      "marketCap": 617088040085,
      "sector": "電子零組件業",
      "theme": "ABF 載板",
      "isNew": false,
      "rankChange": -2,
      "streak": 68
    },
    {
      "symbol": "3189",
      "market": "twse",
      "name": "景碩",
      "price": 739,
      "changePercent": 1.6506189821182942,
      "dollarVolume": 22169743017,
      "marketCap": 389390746640,
      "sector": "半導體業",
      "theme": "ABF 載板",
      "isNew": false,
      "rankChange": 1,
      "streak": 9
    },
    {
      "symbol": "2337",
      "market": "twse",
      "name": "旺宏",
      "price": 172,
      "changePercent": 0,
      "dollarVolume": 19375346899,
      "marketCap": 340785117040,
      "sector": "半導體業",
      "theme": "記憶體",
      "isNew": false,
      "rankChange": -6,
      "streak": 6
    },
    {
      "symbol": "3105",
      "market": "tpex",
      "name": "穩懋",
      "price": 478,
      "changePercent": -8.42911877394636,
      "dollarVolume": 18866547606,
      "marketCap": 202643503552,
      "sector": "半導體業",
      "theme": "砷化鎵",
      "isNew": false,
      "rankChange": 5,
      "streak": 68
    },
    {
      "symbol": "8299",
      "market": "tpex",
      "name": "群聯",
      "price": 2500,
      "changePercent": 2.880658436213992,
      "dollarVolume": 17374766620,
      "marketCap": 552714367500,
      "sector": "半導體業",
      "theme": "NAND 控制IC",
      "isNew": false,
      "rankChange": 5,
      "streak": 68
    },
    {
      "symbol": "4958",
      "market": "twse",
      "name": "臻鼎-KY",
      "price": 587,
      "changePercent": 0,
      "dollarVolume": 16016007717,
      "marketCap": 633620041885,
      "sector": "電子零組件業",
      "theme": "PCB",
      "isNew": false,
      "rankChange": 1,
      "streak": 11
    },
    {
      "symbol": "2317",
      "market": "twse",
      "name": "鴻海",
      "price": 256,
      "changePercent": -1.348747591522158,
      "dollarVolume": 15953563665,
      "marketCap": 3591334048256,
      "sector": "其他電子業",
      "theme": "電子代工",
      "isNew": false,
      "rankChange": -1,
      "streak": 68
    },
    {
      "symbol": "3017",
      "market": "twse",
      "name": "奇鋐",
      "price": 2530,
      "changePercent": 4.329896907216495,
      "dollarVolume": 15909334935,
      "marketCap": 993133807710,
      "sector": "電腦及週邊設備業",
      "theme": "散熱",
      "isNew": true,
      "rankChange": null,
      "streak": 1
    },
    {
      "symbol": "2481",
      "market": "twse",
      "name": "強茂",
      "price": 195,
      "changePercent": 0.7751937984496124,
      "dollarVolume": 13848885103,
      "marketCap": 74512410765,
      "sector": "半導體業",
      "theme": "二極體",
      "isNew": false,
      "rankChange": 6,
      "streak": 2
    },
    {
      "symbol": "2449",
      "market": "twse",
      "name": "京元電子",
      "price": 333.5,
      "changePercent": 1.2139605462822458,
      "dollarVolume": 13780576815,
      "marketCap": 407785479177.5,
      "sector": "半導體業",
      "theme": "封測",
      "isNew": false,
      "rankChange": -5,
      "streak": 4
    },
    {
      "symbol": "5347",
      "market": "tpex",
      "name": "世界",
      "price": 200,
      "changePercent": 7.238605898123325,
      "dollarVolume": 13121716402,
      "marketCap": 375913510000,
      "sector": "半導體業",
      "theme": "晶圓代工",
      "isNew": false,
      "rankChange": 5,
      "streak": 2
    },
    {
      "symbol": "1303",
      "market": "twse",
      "name": "南亞",
      "price": 156,
      "changePercent": 0.9708737864077669,
      "dollarVolume": 11336042273,
      "marketCap": 1237208167884,
      "sector": "塑膠工業",
      "theme": "塑化",
      "isNew": false,
      "rankChange": -14,
      "streak": 8
    },
    {
      "symbol": "3008",
      "market": "twse",
      "name": "大立光",
      "price": 4900,
      "changePercent": -2,
      "dollarVolume": 10056659480,
      "marketCap": 640911165300,
      "sector": "光電業",
      "theme": "光學鏡頭",
      "isNew": false,
      "rankChange": 13,
      "streak": 15
    },
    {
      "symbol": "2383",
      "market": "twse",
      "name": "台光電",
      "price": 5560,
      "changePercent": -2.456140350877193,
      "dollarVolume": 9596314445,
      "marketCap": 1992265393840,
      "sector": "電子零組件業",
      "theme": "CCL",
      "isNew": false,
      "rankChange": 7,
      "streak": 68
    },
    {
      "symbol": "3450",
      "market": "twse",
      "name": "聯鈞",
      "price": 581,
      "changePercent": -5.065359477124183,
      "dollarVolume": 9498471545,
      "marketCap": 84640882942,
      "sector": "半導體業",
      "theme": "光通訊",
      "isNew": false,
      "rankChange": 3,
      "streak": 4
    },
    {
      "symbol": "3374",
      "market": "tpex",
      "name": "精材",
      "price": 312,
      "changePercent": 5.227655986509275,
      "dollarVolume": 9133954868,
      "marketCap": 84665666592,
      "sector": "半導體業",
      "theme": "封測",
      "isNew": false,
      "rankChange": 14,
      "streak": 2
    },
    {
      "symbol": "2368",
      "market": "twse",
      "name": "金像電",
      "price": 1255,
      "changePercent": -0.7905138339920948,
      "dollarVolume": 8689031260,
      "marketCap": 648893904680,
      "sector": "電子零組件業",
      "theme": "PCB",
      "isNew": false,
      "rankChange": 2,
      "streak": 3
    },
    {
      "symbol": "8261",
      "market": "twse",
      "name": "富鼎",
      "price": 246.5,
      "changePercent": -5.1923076923076925,
      "dollarVolume": 8488012857,
      "marketCap": 29303523874.5,
      "sector": "半導體業",
      "theme": "MOSFET",
      "isNew": true,
      "rankChange": null,
      "streak": 1
    },
    {
      "symbol": "2313",
      "market": "twse",
      "name": "華通",
      "price": 240,
      "changePercent": -1.2345679012345678,
      "dollarVolume": 8387538300,
      "marketCap": 286036941360,
      "sector": "電子零組件業",
      "theme": "PCB",
      "isNew": false,
      "rankChange": 3,
      "streak": 68
    },
    {
      "symbol": "6223",
      "market": "tpex",
      "name": "旺矽",
      "price": 7175,
      "changePercent": 7.410179640718563,
      "dollarVolume": 8350991845,
      "marketCap": 703015892075,
      "sector": "半導體業",
      "theme": "半導體設備",
      "isNew": false,
      "rankChange": 13,
      "streak": 2
    },
    {
      "symbol": "3443",
      "market": "twse",
      "name": "創意",
      "price": 4880,
      "changePercent": 3.28042328042328,
      "dollarVolume": 8295987820,
      "marketCap": 653978125680,
      "sector": "半導體業",
      "theme": "IP 矽智財",
      "isNew": false,
      "rankChange": 8,
      "streak": 37
    },
    {
      "symbol": "6683",
      "market": "tpex",
      "name": "雍智科技",
      "price": 1940,
      "changePercent": 9.91501416430595,
      "dollarVolume": 8160380590,
      "marketCap": 53460892340,
      "sector": "半導體業",
      "theme": "IP 矽智財",
      "isNew": true,
      "rankChange": null,
      "streak": 1
    },
    {
      "symbol": "6239",
      "market": "twse",
      "name": "力成",
      "price": 338,
      "changePercent": -1.744186046511628,
      "dollarVolume": 8073427307,
      "marketCap": 256591562292,
      "sector": "半導體業",
      "theme": "封測",
      "isNew": false,
      "rankChange": -12,
      "streak": 9
    },
    {
      "symbol": "3653",
      "market": "twse",
      "name": "健策",
      "price": 3640,
      "changePercent": -5.208333333333334,
      "dollarVolume": 8014042675,
      "marketCap": 534107402920,
      "sector": "電子零組件業",
      "theme": "散熱",
      "isNew": true,
      "rankChange": null,
      "streak": 1
    },
    {
      "symbol": "6274",
      "market": "tpex",
      "name": "台燿",
      "price": 1765,
      "changePercent": 1.729106628242075,
      "dollarVolume": 7914007775,
      "marketCap": 509687234305,
      "sector": "電子零組件業",
      "theme": "CCL",
      "isNew": false,
      "rankChange": -5,
      "streak": 68
    },
    {
      "symbol": "6116",
      "market": "twse",
      "name": "彩晶",
      "price": 19.4,
      "changePercent": 2.1052631578947367,
      "dollarVolume": 7885450934,
      "marketCap": 55457904109.399994,
      "sector": "光電業",
      "theme": "面板",
      "isNew": true,
      "rankChange": null,
      "streak": 1
    },
    {
      "symbol": "6213",
      "market": "twse",
      "name": "聯茂",
      "price": 309,
      "changePercent": 9.9644128113879,
      "dollarVolume": 7865777110,
      "marketCap": 112340725362,
      "sector": "電子零組件業",
      "theme": "CCL",
      "isNew": false,
      "rankChange": 5,
      "streak": 3
    },
    {
      "symbol": "6147",
      "market": "tpex",
      "name": "頎邦",
      "price": 249,
      "changePercent": -3.488372093023256,
      "dollarVolume": 7626405377,
      "marketCap": 185403791211,
      "sector": "半導體業",
      "theme": "驅動IC",
      "isNew": false,
      "rankChange": -15,
      "streak": 2
    },
    {
      "symbol": "2301",
      "market": "twse",
      "name": "光寶科",
      "price": 216.5,
      "changePercent": -3.131991051454139,
      "dollarVolume": 7478421135,
      "marketCap": 501437330689.5,
      "sector": "電腦及週邊設備業",
      "theme": "電源供應器",
      "isNew": false,
      "rankChange": -15,
      "streak": 3
    },
    {
      "symbol": "2345",
      "market": "twse",
      "name": "智邦",
      "price": 2375,
      "changePercent": -2.4640657084188913,
      "dollarVolume": 7210354195,
      "marketCap": 1332655005375,
      "sector": "通信網路業",
      "theme": "網通設備",
      "isNew": false,
      "rankChange": -7,
      "streak": 12
    },
    {
      "symbol": "3665",
      "market": "twse",
      "name": "貿聯-KY",
      "price": 2005,
      "changePercent": 0.25,
      "dollarVolume": 6940264175,
      "marketCap": 391132202025,
      "sector": "其他電子業",
      "theme": "連接器",
      "isNew": true,
      "rankChange": null,
      "streak": 1
    },
    {
      "symbol": "5289",
      "market": "tpex",
      "name": "宜鼎",
      "price": 1795,
      "changePercent": -4.774535809018567,
      "dollarVolume": 6882921260,
      "marketCap": 172925663515,
      "sector": "電腦及週邊設備業",
      "theme": "工控記憶體",
      "isNew": true,
      "rankChange": null,
      "streak": 1
    },
    {
      "symbol": "8358",
      "market": "tpex",
      "name": "金居",
      "price": 638,
      "changePercent": -2.89193302891933,
      "dollarVolume": 6353072148,
      "marketCap": 161151144000,
      "sector": "電子零組件業",
      "theme": "CCL",
      "isNew": false,
      "rankChange": -16,
      "streak": 3
    },
    {
      "symbol": "6669",
      "market": "twse",
      "name": "緯穎",
      "price": 4605,
      "changePercent": -1.4973262032085561,
      "dollarVolume": 6280533110,
      "marketCap": 855796842555,
      "sector": "電腦及週邊設備業",
      "theme": "伺服器",
      "isNew": false,
      "rankChange": -7,
      "streak": 6
    },
    {
      "symbol": "2360",
      "market": "twse",
      "name": "致茂",
      "price": 2160,
      "changePercent": -4.635761589403973,
      "dollarVolume": 6243290885,
      "marketCap": 918530802720,
      "sector": "其他電子業",
      "theme": "自動化設備",
      "isNew": true,
      "rankChange": null,
      "streak": 1
    },
    {
      "symbol": "5425",
      "market": "tpex",
      "name": "台半",
      "price": 132.5,
      "changePercent": -1.1194029850746268,
      "dollarVolume": 5760224770,
      "marketCap": 34911826895,
      "sector": "半導體業",
      "theme": "二極體",
      "isNew": false,
      "rankChange": -24,
      "streak": 2
    },
    {
      "symbol": "2312",
      "market": "twse",
      "name": "金寶",
      "price": 38,
      "changePercent": 9.985528219971057,
      "dollarVolume": 5696112571,
      "marketCap": 57219686018,
      "sector": "其他電子業",
      "theme": "電子代工",
      "isNew": true,
      "rankChange": null,
      "streak": 1
    },
    {
      "symbol": "2379",
      "market": "twse",
      "name": "瑞昱",
      "price": 803,
      "changePercent": -6.952491309385864,
      "dollarVolume": 5663064803,
      "marketCap": 413956650723,
      "sector": "半導體業",
      "theme": "IC 設計",
      "isNew": true,
      "rankChange": null,
      "streak": 1
    }
  ],
  "asOf": "2026-06-24T13:30:00+08:00",
  "generatedAt": "2026-06-24T08:32:05.552Z",
  "source": "twse",
  "aiSource": "gemini",
  "themeSummary": [
    {
      "theme": "晶圓代工",
      "reason": "部分二線晶圓代工廠受惠於成熟製程需求回溫及訂單能見度提升，吸引資金進駐。",
      "symbols": [
        "2303",
        "6770",
        "5347"
      ],
      "count": 3,
      "avgChange": 6.992522377157208
    },
    {
      "theme": "面板",
      "reason": "面板報價止跌回穩，加上庫存去化有成，市場預期產業景氣有望逐步復甦。",
      "symbols": [
        "3481",
        "2409",
        "6116"
      ],
      "count": 3,
      "avgChange": 4.082724152476847
    },
    {
      "theme": "ABF 載板",
      "reason": "ABF載板產業庫存調整接近尾聲，加上AI、HPC等高階應用需求成長，帶動相關個股表現。",
      "symbols": [
        "8046",
        "3189"
      ],
      "count": 2,
      "avgChange": 3.3555625163616773
    },
    {
      "theme": "IP 矽智財",
      "reason": "AI晶片設計需求強勁，帶動IP矽智財廠營收成長動能，市場看好其未來發展潛力。",
      "symbols": [
        "3443",
        "6683"
      ],
      "count": 2,
      "avgChange": 6.597718722364615
    },
    {
      "theme": "封測",
      "reason": "先進封裝技術需求增加，部分封測廠受惠於訂單轉移及新技術導入，營運展望樂觀。",
      "symbols": [
        "2449",
        "3374"
      ],
      "count": 2,
      "avgChange": 3.2208082663957605
    },
    {
      "theme": "CCL",
      "reason": "CCL產業受惠於高階PCB需求成長，加上部分廠商產品組合優化，營收表現亮眼。",
      "symbols": [
        "6274",
        "6213"
      ],
      "count": 2,
      "avgChange": 5.846759719814988
    }
  ],
  "newEntrants": [
    {
      "symbol": "3017",
      "name": "奇鋐",
      "theme": "散熱",
      "changePercent": 4.329896907216495,
      "reason": "AI伺服器水冷散熱題材發酵，受惠AWS、輝達、Meta、Google等新平台量產，外資回補帶動。"
    },
    {
      "symbol": "8261",
      "name": "富鼎",
      "theme": "MOSFET",
      "changePercent": -5.1923076923076925,
      "reason": "功率半導體題材發酵，受惠AI伺服器、資料中心電源需求，國際大廠漲價與去中化轉單效應。"
    },
    {
      "symbol": "6683",
      "name": "雍智科技",
      "theme": "IP 矽智財",
      "changePercent": 9.91501416430595,
      "reason": "近期無明確個股消息，可能受族群輪動帶動。"
    },
    {
      "symbol": "3653",
      "name": "健策",
      "theme": "散熱",
      "changePercent": -5.208333333333334,
      "reason": "AI伺服器散熱需求強勁，GPU與ASIC均熱片出貨看增，法人上修財測。"
    },
    {
      "symbol": "6116",
      "name": "彩晶",
      "theme": "面板",
      "changePercent": 2.1052631578947367,
      "reason": "面板族群資金迴流，受惠世足顯示器需求與車載、工控轉型題材，5月獲利轉盈。"
    },
    {
      "symbol": "3665",
      "name": "貿聯-KY",
      "theme": "連接器",
      "changePercent": 0.25,
      "reason": "近期無明確個股消息，可能受族群輪動帶動。"
    },
    {
      "symbol": "5289",
      "name": "宜鼎",
      "theme": "工控記憶體",
      "changePercent": -4.774535809018567,
      "reason": "近期無明確個股消息，可能受族群輪動帶動。"
    },
    {
      "symbol": "2360",
      "name": "致茂",
      "theme": "自動化設備",
      "changePercent": -4.635761589403973,
      "reason": "近期無明確個股消息，可能受族群輪動帶動。"
    },
    {
      "symbol": "2312",
      "name": "金寶",
      "theme": "電子代工",
      "changePercent": 9.985528219971057,
      "reason": "受惠川普政府推動量子運算產業，金寶與美國量子運算企業合作，切入AI伺服器電源市場。"
    },
    {
      "symbol": "2379",
      "name": "瑞昱",
      "theme": "IC 設計",
      "changePercent": -6.952491309385864,
      "reason": "IC設計族群受惠成熟製程調價，瑞昱網通與連線晶片漲價逾一成，庫存去化尾聲。"
    }
  ],
  "marketBriefing": {
    "highlights": "本日台股成交重點主要受美股費城半導體指數重挫近8%影響，導致台積電（2330）ADR下跌逾6%，並拖累台股大盤重挫逾千點，收盤跌幅2.24%。資金流向呈現明顯的防守態勢，外資大幅賣超1774.18億元，創下史上最大賣超紀錄，三大法人合計賣超逾2102億元。市場在交易AI類股估值過高與獲利了結的擔憂，特別是美光財報公布前的避險情緒，使得半導體、記憶體、IC設計等AI相關族群普遍承壓。然而，部分晶圓代工（如聯電、力積電）、面板（群創、友達）以及ABF載板（南電、景碩）等個股在盤中逆勢走強或跌幅收斂，顯示資金在震盪中尋找具備特定利多或籌碼相對穩定的標的，例如聯電受惠於與英特爾合作題材，群創則因FOPLP先進封裝技術與SpaceX供應鏈傳聞而受關注。",
    "eventsPast": [
      {
        "title": "費城半導體指數重挫近8%，台積電ADR下跌逾6%",
        "detail": "美股2026年6月23日因市場對AI題材估值過高疑慮及美光財報公布前獲利了結賣壓，導致費城半導體指數單日重挫7.87%，台積電ADR下跌6.69%。"
      },
      {
        "title": "台股大盤重挫逾千點，外資創紀錄大賣超",
        "detail": "受美股影響，台股2026年6月24日盤中一度重挫逾1200點，終場下跌1057.05點，外資賣超1774.18億元，創下史上最大單日賣超紀錄。"
      },
      {
        "title": "聯電、力積電逆勢上漲，面板雙雄表現抗跌",
        "detail": "在台股大盤下跌之際，聯電（2303）受惠於與英特爾合作題材，上漲4.71%；力積電（6770）上漲9.03%。群創（3481）和友達（2409）也因先進封裝、低軌衛星等新題材表現抗跌。"
      },
      {
        "title": "記憶體與被動元件族群承壓",
        "detail": "受美股費半指數下跌影響，記憶體族群如南亞科（2408）、華邦電（2344）等出現高檔獲利了結賣壓；被動元件指標股國巨*（2327）在經過一波大漲後也面臨籌碼沉澱壓力。"
      },
      {
        "title": "高盛警告AI市場估值過度拉伸",
        "detail": "高盛全球銀行與市場部策略師Rich Privorotsky指出，當前AI市場估值建立在「資本支出只升不降」的單一假設上，警告一旦主要科技巨頭削減AI基礎建設支出，恐引發全面估值重構。"
      }
    ],
    "eventsUpcoming": [
      {
        "date": "6/25 清晨",
        "title": "美光科技公布2026財年第三季財報",
        "detail": "美光科技（Micron）預計於台灣時間6月25日清晨公布其2026財年第三季（涵蓋3-5月）財報，市場將密切關注其展望，作為判斷記憶體與AI晶片市場未來走勢的重要指標。"
      },
      {
        "date": "本週四",
        "title": "美國5月份個人消費支出 (PCE) 物價指數公布",
        "detail": "本週市場面臨的關鍵考驗是預定週四公布的5月份個人消費支出（PCE）物價指數，這是聯準會偏好的通膨指標，將影響市場對聯準會利率政策的預期。"
      },
      {
        "date": "下週",
        "title": "微軟、谷歌等科技大廠財報",
        "detail": "市場正等待下週微軟、谷歌等科技大廠財報中有關AI變現能力的具體佐證，這將影響AI族群的估值邏輯。"
      },
      {
        "date": "7月",
        "title": "台積電法說會",
        "detail": "台積電（2330）將於下個月舉行法說會，投資人關注其是否有較大利多出現，以及對未來營運展望的看法。"
      },
      {
        "date": "未定",
        "title": "聯準會（Fed）利率決策",
        "detail": "聯準會（Fed）在上週的利率決策會議釋出鷹派訊號後，市場預期的升息時間點已提前，投資人高度關注任何可能釋出訊號的通膨數據，以判斷Fed是否會在近期重啟升息步伐。"
      }
    ]
  }
}